doc/source/conf.py
doc/source/notebooks/GLAM_EXIO_link.py
doc/source/notebooks/adjusting.py
doc/source/notebooks/advanced_group_stressors.py
doc/source/notebooks/aggregation_examples.py
doc/source/notebooks/autodownload.py
doc/source/notebooks/convert.py
doc/source/notebooks/explore.py
doc/source/notebooks/extract_data.py
doc/source/notebooks/full_tutorial.py
doc/source/notebooks/load_save_export.py
doc/source/notebooks/metadata.py
doc/source/notebooks/stressor_characterization.py
doc/source/notebooks/working_with_exiobase.py
doc/source/notebooks/working_with_wiod.py
pymrio/__init__.py
pymrio/version.py
pymrio/core/__init__.py
pymrio/core/constants.py
pymrio/core/fileio.py
pymrio/core/mriosystem.py
pymrio/mrio_models/__init__.py
pymrio/mrio_models/exio2_ixi/__init__.py
pymrio/mrio_models/exio2_ixi/concordance/ALL.txt
pymrio/mrio_models/exio2_ixi/concordance/Africa.txt
pymrio/mrio_models/exio2_ixi/concordance/America.txt
pymrio/mrio_models/exio2_ixi/concordance/AsiaPacific.txt
pymrio/mrio_models/exio2_ixi/concordance/BRIC.txt
pymrio/mrio_models/exio2_ixi/concordance/EU.txt
pymrio/mrio_models/exio2_ixi/concordance/Europe.txt
pymrio/mrio_models/exio2_ixi/concordance/ISIC_A.txt
pymrio/mrio_models/exio2_ixi/concordance/ISIC_B.txt
pymrio/mrio_models/exio2_ixi/concordance/ISIC_C.txt
pymrio/mrio_models/exio2_ixi/concordance/ISIC_D.txt
pymrio/mrio_models/exio2_ixi/concordance/ISIC_E.txt
pymrio/mrio_models/exio2_ixi/concordance/ISIC_F.txt
pymrio/mrio_models/exio2_ixi/concordance/ISIC_G_H.txt
pymrio/mrio_models/exio2_ixi/concordance/ISIC_I.txt
pymrio/mrio_models/exio2_ixi/concordance/ISIC_J_K.txt
pymrio/mrio_models/exio2_ixi/concordance/ISIC_L.txt
pymrio/mrio_models/exio2_ixi/concordance/ISIC_M_N_O.txt
pymrio/mrio_models/exio2_ixi/concordance/ISIC_P.txt
pymrio/mrio_models/exio2_ixi/concordance/MiddleEast.txt
pymrio/mrio_models/exio2_ixi/concordance/OECD.txt
pymrio/mrio_models/exio2_ixi/concordance/RoW.txt
pymrio/mrio_models/exio2_ixi/concordance/__init__.py
pymrio-0.6.3.dist-info/licenses/LICENSE
pymrio-0.6.3.dist-info/METADATA
pymrio-0.6.3.dist-info/WHEEL
pymrio-0.6.3.dist-info/top_level.txt
pymrio-0.6.3.dist-info/RECORD
