Metadata-Version: 2.4
Name: pymrio
Version: 0.6.3
Summary: A python module for automating input output calculations and generating reports
Author-email: Konstantin Stadler <konstantin.stadler@ntnu.no>
Project-URL: Homepage, https://github.com/IndEcol/pymrio
Classifier: Programming Language :: Python :: 3.9
Classifier: Programming Language :: Python :: 3.10
Classifier: Programming Language :: Python :: 3.11
Classifier: Programming Language :: Python :: 3.12
Classifier: Programming Language :: Python :: 3 :: Only
Classifier: License :: OSI Approved :: GNU Lesser General Public License v3 (LGPLv3)
Classifier: Development Status :: 4 - Beta
Classifier: Environment :: Console
Classifier: Intended Audience :: End Users/Desktop
Classifier: Intended Audience :: Developers
Classifier: Intended Audience :: Science/Research
Classifier: Operating System :: MacOS :: MacOS X
Classifier: Operating System :: Microsoft :: Windows
Classifier: Operating System :: POSIX
Classifier: Programming Language :: Python
Classifier: Topic :: Scientific/Engineering
Classifier: Topic :: Utilities
Requires-Python: >=3.9.0
License-File: LICENSE
Requires-Dist: pandas>=2.1
Requires-Dist: pyarrow>=11.0
Requires-Dist: numpy>=1.20
Requires-Dist: matplotlib>=2.0.0
Requires-Dist: requests>=2.18
Requires-Dist: xlrd>1.1.0
Requires-Dist: openpyxl<3.1.1,>=3.0.6
Requires-Dist: docutils>=0.14
Requires-Dist: faker>=18.4.0
Provides-Extra: dev
Requires-Dist: pdbpp; extra == "dev"
Requires-Dist: country_converter>=0.8.0; extra == "dev"
Requires-Dist: ipython; extra == "dev"
Requires-Dist: jupyterlab==3.*; extra == "dev"
Requires-Dist: jupytext; extra == "dev"
Requires-Dist: pynvim; extra == "dev"
Requires-Dist: sphinx>=1.6.4; extra == "dev"
Requires-Dist: sphinx_rtd_theme>=0.2.4; extra == "dev"
Requires-Dist: ipykernel; extra == "dev"
Requires-Dist: debugpy; extra == "dev"
Requires-Dist: nbsphinx; extra == "dev"
Requires-Dist: more-itertools; extra == "dev"
Requires-Dist: poethepoet; extra == "dev"
Provides-Extra: lint
Requires-Dist: black>=22.3.0; extra == "lint"
Requires-Dist: isort>=5.5.2; extra == "lint"
Provides-Extra: test
Requires-Dist: coveralls; extra == "test"
Requires-Dist: coverage[toml]; extra == "test"
Requires-Dist: black; extra == "test"
Requires-Dist: pytest>=5.4.3; extra == "test"
Requires-Dist: pytest-black; extra == "test"
Requires-Dist: pytest-cov>=2.7.0; extra == "test"
Requires-Dist: pytest-datadir; extra == "test"
Requires-Dist: pytest-mypy; extra == "test"
Requires-Dist: pytest-xdist[psutil]; extra == "test"
Requires-Dist: faker; extra == "test"
Requires-Dist: pytest-ruff>=0.5; extra == "test"
Dynamic: license-file
